progpow-0.4.data/data/lib/libprogpow0_9_2.so
progpow-0.4.data/data/lib/libprogpow0_9_3.so
progpow/_libprogpow0_9_3.abi3.so
progpow/__init__.py
progpow/_libprogpow0_9_2.abi3.so
progpow/.libs/libprogpow0_9_3-034bcde1.so
progpow/.libs/libprogpow0_9_2-e9c7251f.so
progpow-0.4.dist-info/WHEEL
progpow-0.4.dist-info/top_level.txt
progpow-0.4.dist-info/METADATA
progpow-0.4.dist-info/RECORD
